jax_unirep/__init__.py
jax_unirep/activations.py
jax_unirep/errors.py
jax_unirep/evotuning.py
jax_unirep/evotuning_models.py
jax_unirep/featurize.py
jax_unirep/layers.py
jax_unirep/losses.py
jax_unirep/optimizers.py
jax_unirep/sampler.py
jax_unirep/utils.py
jax_unirep/version.py
jax_unirep/weights/uniref50/1900_weights/model_weights.pkl
jax_unirep/weights/uniref50/256_weights/model_weights.pkl
jax_unirep/weights/uniref50/64_weights/model_weights.pkl
jax_unirep-2.2.0.dist-info/LICENSE
jax_unirep-2.2.0.dist-info/METADATA
jax_unirep-2.2.0.dist-info/WHEEL
jax_unirep-2.2.0.dist-info/top_level.txt
jax_unirep-2.2.0.dist-info/RECORD
