Metadata-Version: 2.1
Name: jax-unirep
Version: 2.2.0
Summary: A performant and user-friendly reimplementation of UniRep in JAX.
Home-page: https://github.com/ElArkk/jax-unirep
Author: Arkadij Kummer, Eric J. Ma, Ivan Jayapurna
Author-email: arkadij.kummer@gmail.com, ericmajinglong@gmail.com, ivanfj@berkeley.edu
Classifier: Programming Language :: Python :: 3
Classifier: License :: OSI Approved :: GNU General Public License v3 (GPLv3)
Classifier: Operating System :: OS Independent
Classifier: Development Status :: 4 - Beta
Classifier: Intended Audience :: Healthcare Industry
Classifier: Intended Audience :: Science/Research
Classifier: Topic :: Scientific/Engineering
Classifier: Topic :: Scientific/Engineering :: Artificial Intelligence
Classifier: Topic :: Scientific/Engineering :: Bio-Informatics
Classifier: Topic :: Scientific/Engineering :: Chemistry
Requires-Python: >=3.6
License-File: LICENSE
Requires-Dist: jax
Requires-Dist: jaxlib
Requires-Dist: multipledispatch
Requires-Dist: numpy
Requires-Dist: optuna
Requires-Dist: scikit-learn
Requires-Dist: tqdm
